kinkernel/__init__.py
kinkernel/_version.py
kinkernel/py.typed
kinkernel/cells/__init__.py
kinkernel/cells/base.py
kinkernel/cells/cell.py
kinkernel/config/__init__.py
kinkernel/config/base.py
kinkernel/tools/__init__.py
kinkernel/tools/openai_function_cell.py
kinkernel/utils/__init__.py
kinkernel/utils/json_schema_cleaner.py
requirements/__init__.py
tests/__init__.py
tests/cell/__init__.py
tests/cell/test_base.py
tests/cell/test_cell.py
tests/config/__init__.py
tests/config/test_config.py
tests/tools/__init__.py
tests/tools/test_openai_function_cell.py
tests/utils/__init__.py
tests/utils/test_json_schema_cleaner.py
kin_kernel-0.0.5.dist-info/LICENSE
kin_kernel-0.0.5.dist-info/METADATA
kin_kernel-0.0.5.dist-info/WHEEL
kin_kernel-0.0.5.dist-info/top_level.txt
kin_kernel-0.0.5.dist-info/RECORD
