Metadata-Version: 2.1
Name: kin-kernel
Version: 0.0.5
Summary: kin-kernel contain the default templates of Cells that compose a Kin.
Home-page: https://github.com/DigitalKin-ai/kin-kernel
Author: DigitalKin.ai
Author-email: contact@digitalkin.ai
License: CC BY-NC-SA 4.0
Keywords: kin-kernel cells autonomous-agents IoA DigitalKin
Classifier: Development Status :: 3 - Alpha
Classifier: Intended Audience :: Developers
Classifier: License :: Other/Proprietary License
Classifier: Programming Language :: Python :: 3.10
Classifier: Topic :: Software Development :: Libraries
Classifier: Operating System :: OS Independent
Requires-Python: >=3.10
License-File: LICENSE
Requires-Dist: pydantic >=2.5.2
Requires-Dist: pydantic-settings >=2.1.0
Requires-Dist: loguru >=0.7.2
Requires-Dist: opentelemetry-api >=1.21.0
Requires-Dist: opentelemetry-sdk >=1.21.0
